count_pdf_page/__init__.py
count_pdf_page/cli.py
count_pdf_page/core.py
count_pdf_page-0.1.1.dist-info/licenses/LICENSE
count_pdf_page-0.1.1.dist-info/METADATA
count_pdf_page-0.1.1.dist-info/WHEEL
count_pdf_page-0.1.1.dist-info/entry_points.txt
count_pdf_page-0.1.1.dist-info/top_level.txt
count_pdf_page-0.1.1.dist-info/RECORD
