Metadata-Version: 2.4
Name: count-pdf-page
Version: 0.1.1
Summary: A Python package for counting pages in PDF files and generating markdown reports
Author-email: Chih-Hung Hsu <aaronhsu@mail.ntou.edu.tw>
License-Expression: MIT
Project-URL: Homepage, https://github.com/yourusername/count-pdf-page
Project-URL: Repository, https://github.com/yourusername/count-pdf-page
Project-URL: Issues, https://github.com/yourusername/count-pdf-page/issues
Keywords: pdf,page,count,report,markdown
Classifier: Development Status :: 4 - Beta
Classifier: Intended Audience :: End Users/Desktop
Classifier: Operating System :: OS Independent
Classifier: Programming Language :: Python :: 3
Classifier: Programming Language :: Python :: 3.7
Classifier: Programming Language :: Python :: 3.8
Classifier: Programming Language :: Python :: 3.9
Classifier: Programming Language :: Python :: 3.10
Classifier: Programming Language :: Python :: 3.11
Classifier: Programming Language :: Python :: 3.12
Classifier: Topic :: Office/Business
Classifier: Topic :: Utilities
Requires-Python: >=3.7
License-File: LICENSE
Requires-Dist: PyPDF2>=3.0.0
Provides-Extra: dev
Requires-Dist: pytest>=6.0; extra == "dev"
Requires-Dist: pytest-cov; extra == "dev"
Requires-Dist: black; extra == "dev"
Requires-Dist: flake8; extra == "dev"
Requires-Dist: mypy; extra == "dev"
Dynamic: license-file
